cli/__init__.py
cli/cli.py
cli/smartedu_mainmenu.py
core/__init__.py
core/course.py
core/course_manager_txt.py
core/enrollment_manager_txt.py
core/grade_manager_txt.py
core/student.py
core/student_manager_txt.py
core/user.py
data/__init__.py
utils/__init__.py
utils/inputvalidators.py
utils/logger_config.py
smartedu-1.0.0.dist-info/METADATA
smartedu-1.0.0.dist-info/WHEEL
smartedu-1.0.0.dist-info/top_level.txt
smartedu-1.0.0.dist-info/RECORD
