Metadata-Version: 2.4
Name: smartedu
Version: 1.0.0
Summary: CLI backend for student/course/enrollment/grades management
Author: Vinay Kumar Dubba
Requires-Python: >=3.7
Dynamic: requires-python
